tantrum/__init__.py
tantrum/exceptions.py
tantrum/version.py
tantrum/adapters/__init__.py
tantrum/adapters/exceptions.py
tantrum/api_clients/__init__.py
tantrum/api_clients/exceptions.py
tantrum/api_models/__init__.py
tantrum/api_models/exceptions.py
tantrum/api_objects/__init__.py
tantrum/api_objects/exceptions.py
tantrum/api_objects/soap_7_3_314_3424.py
tantrum/api_objects/build_objects/__init__.py
tantrum/api_objects/build_objects/build_objects_from_wsdl.py
tantrum/api_objects/build_objects/download_console_wsdl.py
tantrum/api_objects/build_objects/7_3_314_3424/__init__.py
tantrum/api_objects/build_objects/7_3_314_3424/soap.py
tantrum/auth_methods/__init__.py
tantrum/auth_methods/exceptions.py
tantrum/http_client/__init__.py
tantrum/http_client/exceptions.py
tantrum/results/__init__.py
tantrum/results/exceptions.py
tantrum/utils/__init__.py
tantrum/utils/exceptions.py
tantrum/utils/logs.py
tantrum/utils/tools.py
tantrum/utils/versions.py
tantrum/workflows/__init__.py
tantrum/workflows/exceptions.py
tantrum-1.0.6.dist-info/LICENSE
tantrum-1.0.6.dist-info/METADATA
tantrum-1.0.6.dist-info/WHEEL
tantrum-1.0.6.dist-info/top_level.txt
tantrum-1.0.6.dist-info/RECORD
